dewret/__init__.py
dewret/__main__.py
dewret/_cpython_mod.py
dewret/annotations.py
dewret/cli.py
dewret/core.py
dewret/py.typed
dewret/render.py
dewret/tasks.py
dewret/utils.py
dewret/workflow.py
dewret/backends/__init__.py
dewret/backends/_base.py
dewret/backends/backend_dask.py
dewret/renderers/__init__.py
dewret/renderers/cwl.py
dewret/renderers/snakemake.py
dewret-0.12.1.dist-info/METADATA
dewret-0.12.1.dist-info/WHEEL
dewret-0.12.1.dist-info/licenses/LICENSE
dewret-0.12.1.dist-info/RECORD
