Metadata-Version: 2.4
Name: dewret
Version: 0.12.1
Summary: DEclarative Workflow REndering Tool
Author-email: Phil Weir <phil.weir@flaxandteal.co.uk>, Chris Nixon <chris.nixon@sigma-sc.co.uk>, Ellery Ames <ellery.ames@flaxandteal.co.uk>, Sharon Ingram <sharon.ingram@flaxandteal.co.uk>
License-Expression: Apache-2.0
License-File: LICENSE
Classifier: Programming Language :: Python :: 3
Classifier: Programming Language :: Python :: 3.11
Requires-Python: >=3.11
Requires-Dist: attrs
Requires-Dist: click
Requires-Dist: dask>=2022
Requires-Dist: numpy
Requires-Dist: pyyaml
Requires-Dist: setuptools>=65.5.1
Requires-Dist: sympy
Provides-Extra: docs
Requires-Dist: tmp-fat-portray>=v1.8.0; extra == 'docs'
Provides-Extra: test
Requires-Dist: coverage; extra == 'test'
Requires-Dist: mypy>=1.14.1; extra == 'test'
Requires-Dist: pytest; extra == 'test'
Requires-Dist: ruff; extra == 'test'
